toolbox/__init__.py
toolbox/classes.py
toolbox/functions.py
pdtoolbox-0.0.5.dist-info/LICENSE
pdtoolbox-0.0.5.dist-info/METADATA
pdtoolbox-0.0.5.dist-info/WHEEL
pdtoolbox-0.0.5.dist-info/top_level.txt
pdtoolbox-0.0.5.dist-info/RECORD
