Metadata-Version: 2.1
Name: pdtoolbox
Version: 0.0.5
Summary: Adding of SMS toggle, consumer orders and Influx DB class
Home-page: https://github.com/pedrostanton/toolbox
Author: Pete Davies
Author-email: pedrostanton@gmail.com
License: MIT
Project-URL: Bug Tracker, https://github.com/pedrostanton/toolbox/issues
Platform: UNKNOWN
License-File: LICENSE
Requires-Dist: cbpro
Requires-Dist: pandas
Requires-Dist: python-binance
Requires-Dist: influxdb-client
